svmlight_loader/__init__.py
svmlight_loader/_api.py
svmlight_loader/_sklearn.py
svmlight_loader/tests/__init__.py
svmlight_loader/tests/test_api.py
svmlight_loader-0.8.0.dist-info/COPYING
svmlight_loader-0.8.0.dist-info/METADATA
svmlight_loader-0.8.0.dist-info/WHEEL
svmlight_loader-0.8.0.dist-info/top_level.txt
svmlight_loader-0.8.0.dist-info/RECORD
