Metadata-Version: 2.1
Name: svmlight-loader
Version: 0.8.0
Summary: A Cython-less implementation of the svmlight / libsvm sparse data format
Home-page: https://github.com/Julian/svmlight-loader
Author: Julian Berman
Author-email: Julian+svmlight_loader@GrayVines.com
License: UNKNOWN
Project-URL: Documentation, https://svmlight-loader.readthedocs.io/en/stable/
Project-URL: Source, https://github.com/Julian/svmlight-loader
Project-URL: Issues, https://github.com/Julian/svmlight-loader/issues/
Platform: UNKNOWN
Classifier: Development Status :: 3 - Alpha
Classifier: Operating System :: OS Independent
Classifier: Programming Language :: Python
Classifier: License :: OSI Approved :: MIT License
Classifier: Programming Language :: Python :: 3.6
Classifier: Programming Language :: Python :: 3.7
Classifier: Programming Language :: Python :: 3.8
Classifier: Programming Language :: Python :: 3
Classifier: Programming Language :: Python :: Implementation :: CPython
Classifier: Programming Language :: Python :: Implementation :: PyPy
Requires-Dist: attrs
Requires-Dist: numpy
Requires-Dist: scipy (>=1.4) ; platform_python_implementation != "PyPy"
Requires-Dist: scipy (<1.4) ; platform_python_implementation == "PyPy"
Requires-Dist: importlib-metadata ; python_version < "3.8"
